nbverbose/__init__.py
nbverbose/_nbdev.py
nbverbose/cli.py
nbverbose/showdoc.py
nbverbose-0.0.9.dist-info/METADATA
nbverbose-0.0.9.dist-info/RECORD
nbverbose-0.0.9.dist-info/WHEEL
nbverbose-0.0.9.dist-info/entry_points.txt
nbverbose-0.0.9.dist-info/top_level.txt
