Metadata-Version: 2.1
Name: nbverbose
Version: 0.0.9
Summary: A helpful extension for nbdev geared towards better documentation
Home-page: https://github.com/muellerzr/nbverbose/tree/master/
Author: Zach Mueller
Author-email: muellerzr@gmail.com
License: Apache Software License 2.0
Keywords: nbdev fastai jupyter
Platform: UNKNOWN
Classifier: Development Status :: 3 - Alpha
Classifier: Intended Audience :: Developers
Classifier: Natural Language :: English
Classifier: Programming Language :: Python :: 3.6
Classifier: Programming Language :: Python :: 3.7
Classifier: Programming Language :: Python :: 3.8
Classifier: License :: OSI Approved :: Apache Software License
Requires-Python: >=3.6
Provides-Extra: dev
License-File: LICENSE
Requires-Dist: pip
Requires-Dist: packaging
Requires-Dist: nbdev (<2.0.0)
Requires-Dist: fastcore
Provides-Extra: dev
